{
  "body": {
    "id": "-4cyYdDday",
    "rows": [
      {
        "id": "4NGA6OtXT1",
        "cells": [
          1
        ],
        "values": {
          "_meta": {
            "htmlID": "u_row_1",
            "htmlClassNames": "u_row"
          },
          "anchor": "",
          "columns": false,
          "padding": "0px",
          "hideable": true,
          "deletable": true,
          "draggable": true,
          "selectable": true,
          "hideDesktop": false,
          "duplicatable": true,
          "backgroundColor": "",
          "backgroundImage": {
            "url": "https://cdn.templates.unlayer.com/assets/1679300581877-468636.png",
            "size": "custom",
            "width": 1400,
            "height": 400,
            "repeat": "no-repeat",
            "position": "top-center",
            "fullWidth": true,
            "customPosition": [
              "50%",
              "0%"
            ]
          },
          "displayCondition": null,
          "columnsBackgroundColor": ""
        },
        "columns": [
          {
            "id": "UJ_mT60PtT",
            "values": {
              "_meta": {
                "htmlID": "u_column_1",
                "htmlClassNames": "u_column"
              },
              "border": {},
              "padding": "0px",
              "backgroundColor": ""
            },
            "contents": [
              {
                "id": "EKZjOOusmH",
                "type": "heading",
                "values": {
                  "text": "<strong>Individual Demo</strong>",
                  "_meta": {
                    "htmlID": "u_content_heading_1",
                    "htmlClassNames": "u_content_heading"
                  },
                  "color": "#ffffff",
                  "anchor": "",
                  "fontSize": "30px",
                  "hideable": true,
                  "_override": {
                    "mobile": {
                      "containerPadding": "40px 10px 0px"
                    }
                  },
                  "deletable": true,
                  "draggable": true,
                  "linkStyle": {
                    "inherit": true,
                    "linkColor": "#0000ee",
                    "linkUnderline": true,
                    "linkHoverColor": "#0000ee",
                    "linkHoverUnderline": true
                  },
                  "textAlign": "center",
                  "lineHeight": "140%",
                  "selectable": true,
                  "headingType": "h1",
                  "hideDesktop": false,
                  "duplicatable": true,
                  "containerPadding": "60px 10px 0px",
                  "displayCondition": null
                }
              },
              {
                "id": "cGFFpQN1WP",
                "type": "text",
                "values": {
                  "text": "<p style=\"line-height: 140%;\">Lorem ipsum dolor sit amet, consectetuer adipiscing elit, sed diam nonummy nibh euismod tincidunt ut laoreet dolore magna aliquam erat volutpat. Ut wisi enim ad.</p>",
                  "_meta": {
                    "htmlID": "u_content_text_1",
                    "htmlClassNames": "u_content_text"
                  },
                  "color": "#ced4d9",
                  "anchor": "",
                  "hideable": true,
                  "_override": {
                    "mobile": {
                      "containerPadding": "5px 10px 20px"
                    }
                  },
                  "deletable": true,
                  "draggable": true,
                  "linkStyle": {
                    "inherit": true,
                    "linkColor": "#0000ee",
                    "linkUnderline": true,
                    "linkHoverColor": "#0000ee",
                    "linkHoverUnderline": true
                  },
                  "textAlign": "center",
                  "lineHeight": "140%",
                  "selectable": true,
                  "hideDesktop": false,
                  "duplicatable": true,
                  "containerPadding": "5px 60px 10px",
                  "displayCondition": null
                }
              },
              {
                "id": "rhbR0cK29X",
                "type": "image",
                "values": {
                  "src": {
                    "url": "https://cdn.templates.unlayer.com/assets/1679299847670-Asset%201.png",
                    "width": 844,
                    "height": 615,
                    "maxWidth": "77%",
                    "autoWidth": false
                  },
                  "_meta": {
                    "htmlID": "u_content_image_1",
                    "htmlClassNames": "u_content_image"
                  },
                  "action": {
                    "name": "web",
                    "values": {
                      "href": "",
                      "target": "_blank"
                    }
                  },
                  "anchor": "",
                  "altText": "image",
                  "hideable": true,
                  "_override": {
                    "mobile": {
                      "containerPadding": "10px 10px 36px"
                    }
                  },
                  "deletable": true,
                  "draggable": true,
                  "textAlign": "center",
                  "selectable": true,
                  "hideDesktop": false,
                  "duplicatable": true,
                  "containerPadding": "10px",
                  "displayCondition": null
                }
              }
            ]
          }
        ]
      },
      {
        "id": "059_456wvp",
        "cells": [
          1
        ],
        "values": {
          "_meta": {
            "htmlID": "u_row_2",
            "htmlClassNames": "u_row"
          },
          "anchor": "",
          "columns": false,
          "padding": "0px",
          "hideable": true,
          "deletable": true,
          "draggable": true,
          "selectable": true,
          "hideDesktop": false,
          "duplicatable": true,
          "backgroundColor": "",
          "backgroundImage": {
            "url": "",
            "size": "custom",
            "repeat": "no-repeat",
            "position": "center",
            "fullWidth": true
          },
          "displayCondition": null,
          "columnsBackgroundColor": ""
        },
        "columns": [
          {
            "id": "JSoA38vkMq",
            "values": {
              "_meta": {
                "htmlID": "u_column_2",
                "htmlClassNames": "u_column"
              },
              "border": {},
              "padding": "0px",
              "borderRadius": "0px",
              "backgroundColor": ""
            },
            "contents": [
              {
                "id": "Ba_pifHnix",
                "type": "button",
                "values": {
                  "href": {
                    "name": "web",
                    "attrs": {
                      "href": "{{href}}",
                      "target": "{{target}}"
                    },
                    "values": {
                      "href": "https://www.unlayer.com",
                      "target": "_blank"
                    }
                  },
                  "size": {
                    "width": "30%",
                    "autoWidth": false
                  },
                  "text": "<span style=\"line-height: 16.8px;\">Book a Demo</span>",
                  "_meta": {
                    "htmlID": "u_content_button_2",
                    "htmlClassNames": "u_content_button"
                  },
                  "anchor": "",
                  "border": {
                    "borderTopColor": "#CCC",
                    "borderTopStyle": "solid",
                    "borderTopWidth": "0px",
                    "borderLeftColor": "#CCC",
                    "borderLeftStyle": "solid",
                    "borderLeftWidth": "0px",
                    "borderRightColor": "#CCC",
                    "borderRightStyle": "solid",
                    "borderRightWidth": "0px",
                    "borderBottomColor": "#CCC",
                    "borderBottomStyle": "solid",
                    "borderBottomWidth": "0px"
                  },
                  "padding": "10px 20px",
                  "fontSize": "14px",
                  "hideable": true,
                  "_override": {
                    "mobile": {
                      "size": {
                        "width": "50%",
                        "autoWidth": false
                      }
                    }
                  },
                  "deletable": true,
                  "draggable": true,
                  "textAlign": "center",
                  "lineHeight": "120%",
                  "selectable": true,
                  "borderRadius": "4px",
                  "buttonColors": {
                    "color": "#FFFFFF",
                    "hoverColor": "#FFFFFF",
                    "backgroundColor": "#0b6445",
                    "hoverBackgroundColor": "#3AAEE0"
                  },
                  "duplicatable": true,
                  "calculatedWidth": 174,
                  "calculatedHeight": 37,
                  "containerPadding": "10px",
                  "displayCondition": null
                }
              },
              {
                "id": "X4woEChAYb",
                "type": "heading",
                "values": {
                  "text": "<strong>What Are The Challenges For</strong><br /><strong>Your Email Marketing?</strong>",
                  "_meta": {
                    "htmlID": "u_content_heading_2",
                    "htmlClassNames": "u_content_heading"
                  },
                  "anchor": "",
                  "fontSize": "24px",
                  "hideable": true,
                  "_override": {
                    "mobile": {
                      "fontSize": "20px",
                      "textAlign": "left",
                      "containerPadding": "40px 10px 0px"
                    }
                  },
                  "deletable": true,
                  "draggable": true,
                  "linkStyle": {
                    "inherit": true,
                    "linkColor": "#0000ee",
                    "linkUnderline": true,
                    "linkHoverColor": "#0000ee",
                    "linkHoverUnderline": true
                  },
                  "textAlign": "left",
                  "lineHeight": "140%",
                  "selectable": true,
                  "headingType": "h1",
                  "hideDesktop": false,
                  "duplicatable": true,
                  "containerPadding": "50px 50px 0px",
                  "displayCondition": null
                }
              },
              {
                "id": "7RcdgAHmaO",
                "type": "text",
                "values": {
                  "text": "<p style=\"line-height: 170%;\">Lorem ipsum dolor sit amet, consectetuer adipiscing elit, sed diam nonummy nibh euismod tincidunt ut laoreet dolore magna aliquam erat volutpat. Ut wisi enim ad minim veniam, quis nostrud exerci tation ullamcorper susvero eros et accumsan et iusto odio digni</p>",
                  "_meta": {
                    "htmlID": "u_content_text_3",
                    "htmlClassNames": "u_content_text"
                  },
                  "anchor": "",
                  "hideable": true,
                  "_override": {
                    "mobile": {
                      "textAlign": "left",
                      "lineHeight": "140%",
                      "containerPadding": "10px"
                    }
                  },
                  "deletable": true,
                  "draggable": true,
                  "linkStyle": {
                    "inherit": true,
                    "linkColor": "#0000ee",
                    "linkUnderline": true,
                    "linkHoverColor": "#0000ee",
                    "linkHoverUnderline": true
                  },
                  "textAlign": "justify",
                  "lineHeight": "170%",
                  "selectable": true,
                  "hideDesktop": false,
                  "duplicatable": true,
                  "containerPadding": "10px 50px",
                  "displayCondition": null
                }
              },
              {
                "id": "YeBVQkvOUI",
                "type": "button",
                "values": {
                  "href": {
                    "name": "web",
                    "attrs": {
                      "href": "{{href}}",
                      "target": "{{target}}"
                    },
                    "values": {
                      "href": "https://www.unlayer.com",
                      "target": "_blank"
                    }
                  },
                  "size": {
                    "width": "30%",
                    "autoWidth": false
                  },
                  "text": "<span style=\"line-height: 16.8px;\">Read More</span>",
                  "_meta": {
                    "htmlID": "u_content_button_1",
                    "htmlClassNames": "u_content_button"
                  },
                  "anchor": "",
                  "border": {},
                  "padding": "10px 20px",
                  "fontSize": "14px",
                  "hideable": true,
                  "_override": {
                    "mobile": {
                      "size": {
                        "width": "65%",
                        "autoWidth": false
                      },
                      "textAlign": "left",
                      "containerPadding": "10px 10px 40px"
                    }
                  },
                  "deletable": true,
                  "draggable": true,
                  "textAlign": "left",
                  "lineHeight": "120%",
                  "selectable": true,
                  "hideDesktop": false,
                  "borderRadius": "4px",
                  "buttonColors": {
                    "color": "#FFFFFF",
                    "hoverColor": "#FFFFFF",
                    "backgroundColor": "#0b6445",
                    "hoverBackgroundColor": "#3AAEE0"
                  },
                  "duplicatable": true,
                  "calculatedWidth": 162,
                  "calculatedHeight": 37,
                  "containerPadding": "10px 10px 50px 50px",
                  "displayCondition": null
                }
              }
            ]
          }
        ]
      },
      {
        "id": "orC5U014-U",
        "cells": [
          1
        ],
        "values": {
          "_meta": {
            "htmlID": "u_row_3",
            "htmlClassNames": "u_row"
          },
          "anchor": "",
          "columns": false,
          "padding": "0px",
          "hideable": true,
          "deletable": true,
          "draggable": true,
          "selectable": true,
          "hideDesktop": false,
          "duplicatable": true,
          "backgroundColor": "#eff4f2",
          "backgroundImage": {
            "url": "",
            "size": "custom",
            "repeat": "no-repeat",
            "position": "center",
            "fullWidth": true
          },
          "displayCondition": null,
          "columnsBackgroundColor": ""
        },
        "columns": [
          {
            "id": "3ETVlsncZh",
            "values": {
              "_meta": {
                "htmlID": "u_column_3",
                "htmlClassNames": "u_column"
              },
              "border": {},
              "padding": "0px",
              "borderRadius": "0px",
              "backgroundColor": ""
            },
            "contents": [
              {
                "id": "SheKG7JRTY",
                "type": "heading",
                "values": {
                  "text": "<strong>Solution: How Do We Work?</strong>",
                  "_meta": {
                    "htmlID": "u_content_heading_3",
                    "htmlClassNames": "u_content_heading"
                  },
                  "anchor": "",
                  "fontSize": "22px",
                  "hideable": true,
                  "_override": {
                    "mobile": {
                      "textAlign": "left",
                      "containerPadding": "40px 10px 0px"
                    }
                  },
                  "deletable": true,
                  "draggable": true,
                  "linkStyle": {
                    "inherit": true,
                    "linkColor": "#0000ee",
                    "linkUnderline": true,
                    "linkHoverColor": "#0000ee",
                    "linkHoverUnderline": true
                  },
                  "textAlign": "left",
                  "lineHeight": "140%",
                  "selectable": true,
                  "headingType": "h1",
                  "hideDesktop": false,
                  "duplicatable": true,
                  "containerPadding": "50px 10px 0px 50px",
                  "displayCondition": null
                }
              },
              {
                "id": "yTl1deSS0j",
                "type": "text",
                "values": {
                  "text": "<ol>\n<li style=\"line-height: 28px;\">Lorem ipsum dolor sit amet, consectetuer adipiscing elit, sed diam nonummy nibh euismod tincidunt ut laoreet dolore magna aliquam erat volutpat. Ut wisi enim ad minim veniam.</li>\n<li style=\"line-height: 28px;\">Lorem ipsum dolor sit amet, consectetuer adipiscing elit, sed diam nonummy nibh euismod tincidunt.</li>\n<li style=\"line-height: 28px;\">Lorem ipsum dolor sit amet, consectetuer adipiscing elit, sed diam nonummy nibh euismod tincidunt.</li>\n</ol>",
                  "_meta": {
                    "htmlID": "u_content_text_2",
                    "htmlClassNames": "u_content_text"
                  },
                  "anchor": "",
                  "hideable": true,
                  "_override": {
                    "mobile": {
                      "textAlign": "left",
                      "containerPadding": "0px 10px 40px"
                    }
                  },
                  "deletable": true,
                  "draggable": true,
                  "linkStyle": {
                    "inherit": true,
                    "linkColor": "#0000ee",
                    "linkUnderline": true,
                    "linkHoverColor": "#0000ee",
                    "linkHoverUnderline": true
                  },
                  "textAlign": "justify",
                  "lineHeight": "200%",
                  "selectable": true,
                  "hideDesktop": false,
                  "duplicatable": true,
                  "containerPadding": "0px 50px 50px",
                  "displayCondition": null
                }
              }
            ]
          }
        ]
      },
      {
        "id": "xiWM76JDJg",
        "cells": [
          1,
          2
        ],
        "values": {
          "_meta": {
            "htmlID": "u_row_4",
            "htmlClassNames": "u_row"
          },
          "anchor": "",
          "columns": false,
          "padding": "0px",
          "hideable": true,
          "deletable": true,
          "draggable": true,
          "selectable": true,
          "hideDesktop": false,
          "duplicatable": true,
          "backgroundColor": "",
          "backgroundImage": {
            "url": "",
            "size": "custom",
            "repeat": "no-repeat",
            "position": "center",
            "fullWidth": true
          },
          "displayCondition": null,
          "columnsBackgroundColor": ""
        },
        "columns": [
          {
            "id": "eokFLBWv9h",
            "values": {
              "_meta": {
                "htmlID": "u_column_4",
                "htmlClassNames": "u_column"
              },
              "border": {},
              "padding": "0px",
              "borderRadius": "0px",
              "backgroundColor": ""
            },
            "contents": [
              {
                "id": "0UxrnbnJW2",
                "type": "image",
                "values": {
                  "src": {
                    "url": "https://cdn.templates.unlayer.com/assets/1679305136566-Asse3.png",
                    "width": 726,
                    "height": 725,
                    "maxWidth": "91%",
                    "autoWidth": false
                  },
                  "_meta": {
                    "htmlID": "u_content_image_2",
                    "htmlClassNames": "u_content_image"
                  },
                  "action": {
                    "name": "web",
                    "values": {
                      "href": "",
                      "target": "_blank"
                    }
                  },
                  "anchor": "",
                  "altText": "image",
                  "hideable": true,
                  "_override": {
                    "mobile": {
                      "src": {
                        "maxWidth": "50%",
                        "autoWidth": false
                      },
                      "containerPadding": "40px 10px 0px"
                    }
                  },
                  "deletable": true,
                  "draggable": true,
                  "textAlign": "center",
                  "selectable": true,
                  "hideDesktop": false,
                  "duplicatable": true,
                  "containerPadding": "50px 10px 30px",
                  "displayCondition": null
                }
              }
            ]
          },
          {
            "id": "oMwrVsbf2Y",
            "values": {
              "_meta": {
                "htmlID": "u_column_5",
                "htmlClassNames": "u_column"
              },
              "border": {},
              "padding": "0px",
              "borderRadius": "0px",
              "backgroundColor": ""
            },
            "contents": [
              {
                "id": "CEd7H0A9OD",
                "type": "heading",
                "values": {
                  "text": "<strong>Scarlett John</strong>",
                  "_meta": {
                    "htmlID": "u_content_heading_4",
                    "htmlClassNames": "u_content_heading"
                  },
                  "anchor": "",
                  "fontSize": "22px",
                  "hideable": true,
                  "_override": {
                    "mobile": {
                      "textAlign": "center",
                      "containerPadding": "20px 10px 0px"
                    }
                  },
                  "deletable": true,
                  "draggable": true,
                  "linkStyle": {
                    "inherit": true,
                    "linkColor": "#0000ee",
                    "linkUnderline": true,
                    "linkHoverColor": "#0000ee",
                    "linkHoverUnderline": true
                  },
                  "textAlign": "left",
                  "fontFamily": {
                    "url": "https://fonts.googleapis.com/css?family=Open+Sans:400,700",
                    "label": "Open Sans",
                    "value": "'Open Sans',sans-serif",
                    "defaultFont": true
                  },
                  "lineHeight": "140%",
                  "selectable": true,
                  "headingType": "h1",
                  "hideDesktop": false,
                  "duplicatable": true,
                  "containerPadding": "65px 10px 0px",
                  "displayCondition": null
                }
              },
              {
                "id": "Uu3pS27mP_",
                "type": "text_deprecated",
                "values": {
                  "text": "<p style=\"font-size: 14px; line-height: 140%;\"><span style=\"font-family: 'Open Sans', sans-serif; font-size: 14px; line-height: 19.6px;\">Sales &amp; Marketing</span></p>",
                  "_meta": {
                    "htmlID": "u_content_text_deprecated_1",
                    "htmlClassNames": "u_content_text"
                  },
                  "color": "#3d3d3d",
                  "anchor": "",
                  "hideable": true,
                  "_override": {
                    "mobile": {
                      "textAlign": "center"
                    }
                  },
                  "deletable": true,
                  "draggable": true,
                  "linkStyle": {
                    "inherit": true,
                    "linkColor": "#0000ee",
                    "linkUnderline": true,
                    "linkHoverColor": "#0000ee",
                    "linkHoverUnderline": true
                  },
                  "textAlign": "left",
                  "lineHeight": "140%",
                  "selectable": true,
                  "hideDesktop": false,
                  "duplicatable": true,
                  "containerPadding": "0px 10px",
                  "displayCondition": null
                }
              },
              {
                "id": "66V7VK-yn2",
                "type": "social",
                "values": {
                  "_meta": {
                    "htmlID": "u_content_social_1",
                    "htmlClassNames": "u_content_social"
                  },
                  "align": "left",
                  "icons": {
                    "icons": [
                      {
                        "url": "https://www.facebook.com/unlayer",
                        "name": "Facebook"
                      },
                      {
                        "url": "https://twitter.com/unlayerapp",
                        "name": "Twitter"
                      },
                      {
                        "url": "https://www.linkedin.com/company/unlayer/mycompany/",
                        "name": "LinkedIn"
                      },
                      {
                        "url": "https://www.instagram.com/unlayer_official/",
                        "name": "Instagram"
                      },
                      {
                        "url": "https://hu.pinterest.com/unlayer/",
                        "name": "Pinterest"
                      }
                    ],
                    "editor": {
                      "data": {
                        "customIcons": [],
                        "customOptions": [],
                        "showDefaultIcons": true,
                        "showDefaultOptions": true
                      }
                    },
                    "iconType": "circle-black"
                  },
                  "anchor": "",
                  "spacing": 10,
                  "hideable": true,
                  "_override": {
                    "mobile": {
                      "containerPadding": "10px 10px 10px 55px"
                    }
                  },
                  "deletable": true,
                  "draggable": true,
                  "selectable": true,
                  "hideDesktop": false,
                  "duplicatable": true,
                  "containerPadding": "10px",
                  "displayCondition": null
                }
              },
              {
                "id": "-lLWCWValG",
                "type": "text_deprecated",
                "values": {
                  "text": "<p style=\"font-size: 14px; line-height: 140%;\"><span style=\"font-family: 'Open Sans', sans-serif; font-size: 14px; line-height: 19.6px;\">+123 456 7890  |  unlayer@gmail.com</span></p>",
                  "_meta": {
                    "htmlID": "u_content_text_deprecated_2",
                    "htmlClassNames": "u_content_text"
                  },
                  "color": "#3d3d3d",
                  "anchor": "",
                  "hideable": true,
                  "_override": {
                    "mobile": {
                      "textAlign": "center",
                      "containerPadding": "0px 10px 30px"
                    }
                  },
                  "deletable": true,
                  "draggable": true,
                  "linkStyle": {
                    "inherit": true,
                    "linkColor": "#0000ee",
                    "linkUnderline": true,
                    "linkHoverColor": "#0000ee",
                    "linkHoverUnderline": true
                  },
                  "textAlign": "left",
                  "lineHeight": "140%",
                  "selectable": true,
                  "hideDesktop": false,
                  "duplicatable": true,
                  "containerPadding": "0px 10px 10px",
                  "displayCondition": null
                }
              }
            ]
          }
        ]
      },
      {
        "id": "U8xTjs5ETd",
        "cells": [
          1
        ],
        "values": {
          "_meta": {
            "htmlID": "u_row_5",
            "htmlClassNames": "u_row"
          },
          "anchor": "",
          "columns": false,
          "padding": "0px",
          "hideable": true,
          "deletable": true,
          "draggable": true,
          "selectable": true,
          "hideDesktop": false,
          "duplicatable": true,
          "backgroundColor": "",
          "backgroundImage": {
            "url": "",
            "size": "custom",
            "repeat": "no-repeat",
            "position": "center",
            "fullWidth": true
          },
          "displayCondition": null,
          "columnsBackgroundColor": ""
        },
        "columns": [
          {
            "id": "QwjYvyqt2T",
            "values": {
              "_meta": {
                "htmlID": "u_column_6",
                "htmlClassNames": "u_column"
              },
              "border": {},
              "padding": "0px",
              "borderRadius": "0px",
              "backgroundColor": ""
            },
            "contents": [
              {
                "id": "bxh42co1y7",
                "type": "divider",
                "values": {
                  "_meta": {
                    "htmlID": "u_content_divider_1",
                    "htmlClassNames": "u_content_divider"
                  },
                  "width": "100%",
                  "anchor": "",
                  "border": {
                    "borderTopColor": "#BBBBBB",
                    "borderTopStyle": "solid",
                    "borderTopWidth": "1px"
                  },
                  "hideable": true,
                  "deletable": true,
                  "draggable": true,
                  "textAlign": "center",
                  "selectable": true,
                  "hideDesktop": false,
                  "duplicatable": true,
                  "containerPadding": "0px 0px 10px",
                  "displayCondition": null
                }
              },
              {
                "id": "OoFSuwIXQp",
                "type": "text",
                "values": {
                  "text": "<p style=\"line-height: 140%;\">Lorem ipsum dolor sit amet, consectetuer adip iscing elit sed diam nonu.</p>",
                  "_meta": {
                    "htmlID": "u_content_text_4",
                    "htmlClassNames": "u_content_text"
                  },
                  "anchor": "",
                  "hideable": true,
                  "_override": {
                    "mobile": {
                      "textAlign": "center",
                      "containerPadding": "10px 10px 40px"
                    }
                  },
                  "deletable": true,
                  "draggable": true,
                  "linkStyle": {
                    "inherit": true,
                    "linkColor": "#0000ee",
                    "linkUnderline": true,
                    "linkHoverColor": "#0000ee",
                    "linkHoverUnderline": true
                  },
                  "textAlign": "left",
                  "lineHeight": "140%",
                  "selectable": true,
                  "hideDesktop": false,
                  "duplicatable": true,
                  "containerPadding": "10px 10px 30px",
                  "displayCondition": null
                }
              }
            ]
          }
        ]
      }
    ],
    "values": {
      "_meta": {
        "htmlID": "u_body",
        "htmlClassNames": "u_body"
      },
      "linkStyle": {
        "body": true,
        "linkColor": "#0000ee",
        "linkUnderline": true,
        "linkHoverColor": "#0000ee",
        "linkHoverUnderline": true
      },
      "textColor": "#000000",
      "fontFamily": {
        "url": "https://fonts.googleapis.com/css?family=Open+Sans:400,700",
        "label": "Open Sans",
        "value": "'Open Sans',sans-serif",
        "weights": null,
        "defaultFont": true
      },
      "popupWidth": "600px",
      "popupHeight": "auto",
      "borderRadius": "10px",
      "contentAlign": "center",
      "contentWidth": 600,
      "popupPosition": "center",
      "preheaderText": "",
      "backgroundColor": "#ffffff",
      "backgroundImage": {
        "url": "",
        "size": "custom",
        "repeat": "no-repeat",
        "position": "center",
        "fullWidth": true
      },
      "contentVerticalAlign": "center",
      "popupBackgroundColor": "#FFFFFF",
      "popupBackgroundImage": {
        "url": "",
        "size": "cover",
        "repeat": "no-repeat",
        "position": "center",
        "fullWidth": true
      },
      "popupCloseButton_action": {
        "name": "close_popup",
        "attrs": {
          "onClick": "document.querySelector('.u-popup-container').style.display = 'none';"
        }
      },
      "popupCloseButton_margin": "0px",
      "popupCloseButton_position": "top-right",
      "popupCloseButton_iconColor": "#000000",
      "popupOverlay_backgroundColor": "rgba(0, 0, 0, 0.1)",
      "popupCloseButton_borderRadius": "0px",
      "popupCloseButton_backgroundColor": "#DDDDDD"
    }
  },
  "counters": {
    "u_row": 5,
    "u_column": 6,
    "u_content_text": 4,
    "u_content_image": 2,
    "u_content_button": 2,
    "u_content_social": 1,
    "u_content_divider": 1,
    "u_content_heading": 4,
    "u_content_text_deprecated": 2
  },
  "schemaVersion": 12
}